LICENSE.txt
README.md
setup.py
./__init__.py
./cli.py
./faction/__init__.py
./faction/program_id.py
./faction/accounts/__init__.py
./faction/accounts/player_faction_data.py
./faction/errors/__init__.py
./faction/errors/anchor.py
./faction/errors/custom.py
./faction/instructions/__init__.py
./faction/instructions/process_enlist_player.py
./marketplace/__init__.py
./marketplace/program_id.py
./marketplace/accounts/__init__.py
./marketplace/accounts/market_vars.py
./marketplace/accounts/open_orders_counter.py
./marketplace/accounts/order_account.py
./marketplace/accounts/registered_currency.py
./marketplace/errors/__init__.py
./marketplace/errors/anchor.py
./marketplace/errors/custom.py
./marketplace/instructions/__init__.py
./marketplace/instructions/deregister_currency.py
./marketplace/instructions/initialize_marketplace.py
./marketplace/instructions/initialize_open_orders_counter.py
./marketplace/instructions/process_cancel.py
./marketplace/instructions/process_exchange.py
./marketplace/instructions/process_initialize_buy.py
./marketplace/instructions/process_initialize_sell.py
./marketplace/instructions/register_currency.py
./marketplace/instructions/update_currency_royalty.py
./marketplace/instructions/update_currency_vault.py
./marketplace/types/__init__.py
./marketplace/types/order_side.py
./marketplace/types/royalty_tier.py
./marketplace/types/token_type.py
./score/__init__.py
./score/program_id.py
./score/accounts/__init__.py
./score/accounts/score_vars.py
./score/accounts/score_vars_ship.py
./score/accounts/ship_staking.py
./score/errors/__init__.py
./score/errors/anchor.py
./score/errors/custom.py
./score/instructions/__init__.py
./score/instructions/process_close_accounts.py
./score/instructions/process_deregister_ship.py
./score/instructions/process_harvest.py
./score/instructions/process_initial_deposit.py
./score/instructions/process_initialize.py
./score/instructions/process_partial_deposit.py
./score/instructions/process_rearm.py
staratlaspy.egg-info/LICENSE.txt
staratlaspy.egg-info/PKG-INFO
staratlaspy.egg-info/SOURCES.txt
staratlaspy.egg-info/dependency_links.txt
staratlaspy.egg-info/entry_points.txt
staratlaspy.egg-info/requires.txt
staratlaspy.egg-info/top_level.txt