Metadata-Version: 2.1
Name: staratlaspy
Version: 0.1.31
Summary: Python module for parsing staratlas instructions (based on anchorpy).
Author: Vlad Smirnov
Author-email: vlad@theclubguild.com
License: Creative Commons Attribution-NonCommercial-NoDerivatives 4.0 International Public License
Classifier: Development Status :: 3 - Alpha
Classifier: Intended Audience :: Developers
Classifier: Topic :: Software Development :: Libraries :: Python Modules
Classifier: Programming Language :: Python :: 3
Requires-Python: >=3.9, <4
License-File: LICENSE.txt
